xiangshi/__init__.py
xiangshi-4.2.3.dist-info/LICENSE
xiangshi-4.2.3.dist-info/METADATA
xiangshi-4.2.3.dist-info/WHEEL
xiangshi-4.2.3.dist-info/top_level.txt
xiangshi-4.2.3.dist-info/RECORD
