Metadata-Version: 2.1
Name: xiangshi
Version: 4.2.3
Summary: 中文文本相似度计算器 - 现已改名为Xiangsi
Home-page: https://github.com/kiwirafe/xiangsi
Author: kiwirafe
Author-email: kiwirafe@gmail.com
Project-URL: Github, https://github.com/kiwirafe/xiangsi
Classifier: Programming Language :: Python :: 3
Classifier: License :: OSI Approved :: MIT License
Classifier: Operating System :: OS Independent
Requires-Python: >=3.4
License-File: LICENSE
Requires-Dist: xiangsi
